pinballmap/__init__.py
pinballmap/__main__.py
pinballmap/auth.py
pinballmap/cli.py
pinballmap/client.py
pinballmap/constants.py
pinballmap/exceptions.py
pinballmap/name_matching.py
pinballmap/utilities.py
pinballmap-0.4.6.dist-info/LICENSE.txt
pinballmap-0.4.6.dist-info/METADATA
pinballmap-0.4.6.dist-info/WHEEL
pinballmap-0.4.6.dist-info/entry_points.txt
pinballmap-0.4.6.dist-info/RECORD
