Metadata-Version: 2.1
Name: pinballmap
Version: 0.4.6
Summary: Python client for the Pinball Map API
License: MIT
Keywords: pinball,map,API
Author: Duna Csandl
Author-email: marinas.bobble-05@icloud.com
Requires-Python: >=3.11,<4.0.0
Classifier: License :: OSI Approved :: MIT License
Classifier: Programming Language :: Python :: 3
Classifier: Programming Language :: Python :: 3.11
Classifier: Programming Language :: Python :: 3.12
Provides-Extra: jupyter
Requires-Dist: requests (>=2.32.3,<3.0.0)
Requires-Dist: tabulate (>=0.9.0,<0.10.0)
